betamax_serializers/__init__.py
betamax_serializers/pretty_json.py
betamax_serializers/yaml11.py
betamax_serializers-0.2.1.dist-info/AUTHORS.rst
betamax_serializers-0.2.1.dist-info/LICENSE
betamax_serializers-0.2.1.dist-info/METADATA
betamax_serializers-0.2.1.dist-info/WHEEL
betamax_serializers-0.2.1.dist-info/top_level.txt
betamax_serializers-0.2.1.dist-info/RECORD
